topsis/__init__.py
topsis/__main__.py
topsis_mannat_102117185-1.0.2.dist-info/METADATA
topsis_mannat_102117185-1.0.2.dist-info/WHEEL
topsis_mannat_102117185-1.0.2.dist-info/entry_points.txt
topsis_mannat_102117185-1.0.2.dist-info/top_level.txt
topsis_mannat_102117185-1.0.2.dist-info/RECORD
